{
  "id": "OSM-br-telegram",
  "type": "telegram",
  "locationSet": {"include": ["br"]},
  "languageCodes": ["pt"],
  "url": "https://t.me/OSMBrasil_Comunidade",
  "order": 1,
  "strings": {
    "name": "OpenStreetMap Brasil Telegram",
    "description": "Join the OpenStreetMap Brasil community on Telegram",
    "extendedDescription": "Join the community to learn more about OpenStreetMap, ask questions or participate in our meetings. Everyone is welcome!"
  },
  "contacts": [
    {"name": "Vitor George", "email": "vitor.george@gmail.com"}
  ]
}
