{
  "id": "osm-de",
  "type": "osm-lc",
  "locationSet": {"include": ["de"]},
  "languageCodes": ["de"],
  "strings": {
    "community": "OpenStreetMap Germany",
    "description": "The platform for information on OpenStreetMap in Germany",
    "url": "https://www.openstreetmap.de/"
  },
  "resolved": {
    "name": "OpenStreetMap Germany",
    "description": "The platform for information on OpenStreetMap in Germany",
    "url": "https://www.openstreetmap.de/"
  },
  "contacts": [{"name": "FOSSGIS e.V.", "email": "info@fossgis.de"}]
}
