{
  "id": "co-telegram",
  "type": "telegram",
  "account": "osmco",
  "locationSet": {"include": ["co"]},
  "languageCodes": ["es"],
  "order": 13,
  "strings": {
    "community": "OSM Colombia",
    "communityID": "openstreetmapcolombia",
    "name": "Conversation group on {community} in Telegram",
    "description": "Open discussions on topics of interest to the entire community. It is the most active channel"

  },
  "contacts": [
    {"name": "Contacto Colombia", "email": "colombia@osm.lat"}
  ]
}
